pythonql/Ast.py
pythonql/Executor.py
pythonql/PQTable.py
pythonql/PQTuple.py
pythonql/Rewriter.py
pythonql/RunPYQL.py
pythonql/__init__.py
pythonql/debug.py
pythonql/helpers.py
pythonql/pandas_lib.py
pythonql/settings.py
pythonql/algebra/__init__.py
pythonql/algebra/operator.py
pythonql/algebra/operators.py
pythonql/codec/__init__.py
pythonql/codec/register.py
pythonql/parser/Preprocessor.py
pythonql/parser/PythonQLLexer.py
pythonql/parser/PythonQLParser.py
pythonql/parser/__init__.py
pythonql/parser/parsertab.py
pythonql/sources/__init__.py
pythonql/sources/mysql.py
pythonql/sources/postgresql.py
pythonql/sources/source.py
pythonql3-0.9.81.dist-info/LICENSE.md
pythonql3-0.9.81.dist-info/METADATA
pythonql3-0.9.81.dist-info/WHEEL
pythonql3-0.9.81.dist-info/top_level.txt
pythonql3-0.9.81.dist-info/RECORD
