Metadata-Version: 2.1
Name: pythonql3
Version: 0.9.81
Summary: PythonQL Query Language Extension
Home-page: http://www.pythonql.org
Author: Pavel Velikhov
Author-email: pavel.velikhov@gmail.com
License: MIT
Keywords: query extension
Platform: UNKNOWN
Classifier: Development Status :: 3 - Alpha
Classifier: License :: OSI Approved :: MIT License
License-File: LICENSE.md
Requires-Dist: ply (>=3.9)
